<?xml version="1.0" encoding="utf-8"?>
<TextureAtlas imagePath="PanLoreDead.png">
	<!-- Created with Adobe Animate version 21.0.1.37179 -->
	<!-- http://www.adobe.com/products/animate.html -->
	<SubTexture name="End0000" x="4183" y="2069" width="824" height="490" frameX="-13" frameY="-125" frameWidth="857" frameHeight="619"/>
	<SubTexture name="End0001" x="5992" y="2694" width="725" height="526" frameX="-13" frameY="-89" frameWidth="857" frameHeight="619"/>
	<SubTexture name="End0002" x="5992" y="2694" width="725" height="526" frameX="-13" frameY="-89" frameWidth="857" frameHeight="619"/>
	<SubTexture name="End0003" x="977" y="2687" width="746" height="513" frameX="-13" frameY="-102" frameWidth="857" frameHeight="619"/>
	<SubTexture name="End0004" x="977" y="2687" width="746" height="513" frameX="-13" frameY="-102" frameWidth="857" frameHeight="619"/>
	<SubTexture name="End0005" x="6844" y="2017" width="844" height="490" frameX="-13" frameY="-125" frameWidth="857" frameHeight="619"/>
	<SubTexture name="End0006" x="6844" y="2017" width="844" height="490" frameX="-13" frameY="-125" frameWidth="857" frameHeight="619"/>
	<SubTexture name="End0007" x="3216" y="2075" width="805" height="490" frameX="-13" frameY="-125" frameWidth="857" frameHeight="619"/>
	<SubTexture name="End0008" x="3216" y="2075" width="805" height="490" frameX="-13" frameY="-125" frameWidth="857" frameHeight="619"/>
	<SubTexture name="End0009" x="3216" y="2075" width="805" height="490" frameX="-13" frameY="-125" frameWidth="857" frameHeight="619"/>
	<SubTexture name="End0010" x="3216" y="2075" width="805" height="490" frameX="-13" frameY="-125" frameWidth="857" frameHeight="619"/>
	<SubTexture name="End0011" x="3216" y="2075" width="805" height="490" frameX="-13" frameY="-125" frameWidth="857" frameHeight="619"/>
	<SubTexture name="End0012" x="3216" y="2075" width="805" height="490" frameX="-13" frameY="-125" frameWidth="857" frameHeight="619"/>
	<SubTexture name="End0013" x="3216" y="2075" width="805" height="490" frameX="-13" frameY="-125" frameWidth="857" frameHeight="619"/>
	<SubTexture name="End0014" x="3216" y="2075" width="805" height="490" frameX="-13" frameY="-125" frameWidth="857" frameHeight="619"/>
	<SubTexture name="End0015" x="3216" y="2075" width="805" height="490" frameX="-13" frameY="-125" frameWidth="857" frameHeight="619"/>
	<SubTexture name="End0016" x="3216" y="2075" width="805" height="490" frameX="-13" frameY="-125" frameWidth="857" frameHeight="619"/>
	<SubTexture name="End0017" x="3216" y="2075" width="805" height="490" frameX="-13" frameY="-125" frameWidth="857" frameHeight="619"/>
	<SubTexture name="End0018" x="3216" y="2075" width="805" height="490" frameX="-13" frameY="-125" frameWidth="857" frameHeight="619"/>
	<SubTexture name="End0019" x="3216" y="2075" width="805" height="490" frameX="-13" frameY="-125" frameWidth="857" frameHeight="619"/>
	<SubTexture name="End0020" x="3216" y="2075" width="805" height="490" frameX="-13" frameY="-125" frameWidth="857" frameHeight="619"/>
	<SubTexture name="End0021" x="3216" y="2075" width="805" height="490" frameX="-13" frameY="-125" frameWidth="857" frameHeight="619"/>
	<SubTexture name="End0022" x="3216" y="2075" width="805" height="490" frameX="-13" frameY="-125" frameWidth="857" frameHeight="619"/>
	<SubTexture name="End0023" x="3216" y="2075" width="805" height="490" frameX="-13" frameY="-125" frameWidth="857" frameHeight="619"/>
	<SubTexture name="End0024" x="3216" y="2075" width="805" height="490" frameX="-13" frameY="-125" frameWidth="857" frameHeight="619"/>
	<SubTexture name="End0025" x="3216" y="2075" width="805" height="490" frameX="-13" frameY="-125" frameWidth="857" frameHeight="619"/>
	<SubTexture name="End0026" x="3216" y="2075" width="805" height="490" frameX="-13" frameY="-125" frameWidth="857" frameHeight="619"/>
	<SubTexture name="End0027" x="100" y="2136" width="805" height="490" frameX="-13" frameY="-125" frameWidth="857" frameHeight="619"/>
	<SubTexture name="End0028" x="100" y="2136" width="805" height="490" frameX="-13" frameY="-125" frameWidth="857" frameHeight="619"/>
	<SubTexture name="End0029" x="100" y="2136" width="805" height="490" frameX="-13" frameY="-125" frameWidth="857" frameHeight="619"/>
	<SubTexture name="End0030" x="100" y="2136" width="805" height="490" frameX="-13" frameY="-125" frameWidth="857" frameHeight="619"/>
	<SubTexture name="End0031" x="100" y="2136" width="805" height="490" frameX="-13" frameY="-125" frameWidth="857" frameHeight="619"/>
	<SubTexture name="End0032" x="100" y="2136" width="805" height="490" frameX="-13" frameY="-125" frameWidth="857" frameHeight="619"/>
	<SubTexture name="End0033" x="100" y="2136" width="805" height="490" frameX="-13" frameY="-125" frameWidth="857" frameHeight="619"/>
	<SubTexture name="End0034" x="100" y="2136" width="805" height="490" frameX="-13" frameY="-125" frameWidth="857" frameHeight="619"/>
	<SubTexture name="End0035" x="100" y="2136" width="805" height="490" frameX="-13" frameY="-125" frameWidth="857" frameHeight="619"/>
	<SubTexture name="End0036" x="100" y="2136" width="805" height="490" frameX="-13" frameY="-125" frameWidth="857" frameHeight="619"/>
	<SubTexture name="End0037" x="100" y="2136" width="805" height="490" frameX="-13" frameY="-125" frameWidth="857" frameHeight="619"/>
	<SubTexture name="End0038" x="100" y="2136" width="805" height="490" frameX="-13" frameY="-125" frameWidth="857" frameHeight="619"/>
	<SubTexture name="End0039" x="100" y="2136" width="805" height="490" frameX="-13" frameY="-125" frameWidth="857" frameHeight="619"/>
	<SubTexture name="End0040" x="100" y="2136" width="805" height="490" frameX="-13" frameY="-125" frameWidth="857" frameHeight="619"/>
	<SubTexture name="End0041" x="100" y="2136" width="805" height="490" frameX="-13" frameY="-125" frameWidth="857" frameHeight="619"/>
	<SubTexture name="End0042" x="100" y="2136" width="805" height="490" frameX="-13" frameY="-125" frameWidth="857" frameHeight="619"/>
	<SubTexture name="End0043" x="100" y="2136" width="805" height="490" frameX="-13" frameY="-125" frameWidth="857" frameHeight="619"/>
	<SubTexture name="End0044" x="100" y="2136" width="805" height="490" frameX="-13" frameY="-125" frameWidth="857" frameHeight="619"/>
	<SubTexture name="End0045" x="100" y="2136" width="805" height="490" frameX="-13" frameY="-125" frameWidth="857" frameHeight="619"/>
	<SubTexture name="End0046" x="4093" y="2631" width="806" height="479" frameX="-12" frameY="-138" frameWidth="857" frameHeight="619"/>
	<SubTexture name="End0047" x="4093" y="2631" width="806" height="479" frameX="-12" frameY="-138" frameWidth="857" frameHeight="619"/>
	<SubTexture name="End0048" x="977" y="2136" width="818" height="479" frameX="0" frameY="-138" frameWidth="857" frameHeight="619"/>
	<SubTexture name="End0049" x="977" y="2136" width="818" height="479" frameX="0" frameY="-138" frameWidth="857" frameHeight="619"/>
	<SubTexture name="End0050" x="977" y="2136" width="818" height="479" frameX="0" frameY="-138" frameWidth="857" frameHeight="619"/>
	<SubTexture name="End0051" x="977" y="2136" width="818" height="479" frameX="0" frameY="-138" frameWidth="857" frameHeight="619"/>
	<SubTexture name="End0052" x="977" y="2136" width="818" height="479" frameX="0" frameY="-138" frameWidth="857" frameHeight="619"/>
	<SubTexture name="End0053" x="977" y="2136" width="818" height="479" frameX="0" frameY="-138" frameWidth="857" frameHeight="619"/>
	<SubTexture name="End0054" x="977" y="2136" width="818" height="479" frameX="0" frameY="-138" frameWidth="857" frameHeight="619"/>
	<SubTexture name="End0055" x="977" y="2136" width="818" height="479" frameX="0" frameY="-138" frameWidth="857" frameHeight="619"/>
	<SubTexture name="End0056" x="977" y="2136" width="818" height="479" frameX="0" frameY="-138" frameWidth="857" frameHeight="619"/>
	<SubTexture name="End0057" x="5153" y="2006" width="767" height="619" frameX="-51" frameY="0" frameWidth="857" frameHeight="619"/>
	<SubTexture name="End0058" x="5153" y="2006" width="767" height="619" frameX="-51" frameY="0" frameWidth="857" frameHeight="619"/>
	<SubTexture name="End0059" x="5992" y="2017" width="780" height="605" frameX="-38" frameY="-14" frameWidth="857" frameHeight="619"/>
	<SubTexture name="End0060" x="5992" y="2017" width="780" height="605" frameX="-38" frameY="-14" frameWidth="857" frameHeight="619"/>
	<SubTexture name="End0061" x="5992" y="2017" width="780" height="605" frameX="-38" frameY="-14" frameWidth="857" frameHeight="619"/>
	<SubTexture name="End0062" x="5992" y="2017" width="780" height="605" frameX="-38" frameY="-14" frameWidth="857" frameHeight="619"/>
	<SubTexture name="End0063" x="5992" y="2017" width="780" height="605" frameX="-38" frameY="-14" frameWidth="857" frameHeight="619"/>
	<SubTexture name="End0064" x="5992" y="2017" width="780" height="605" frameX="-38" frameY="-14" frameWidth="857" frameHeight="619"/>
	<SubTexture name="End0065" x="5992" y="2017" width="780" height="605" frameX="-38" frameY="-14" frameWidth="857" frameHeight="619"/>
	<SubTexture name="End0066" x="5992" y="2017" width="780" height="605" frameX="-38" frameY="-14" frameWidth="857" frameHeight="619"/>
	<SubTexture name="End0067" x="5992" y="2017" width="780" height="605" frameX="-38" frameY="-14" frameWidth="857" frameHeight="619"/>
	<SubTexture name="End0068" x="5992" y="2017" width="780" height="605" frameX="-38" frameY="-14" frameWidth="857" frameHeight="619"/>
	<SubTexture name="End0069" x="5992" y="2017" width="780" height="605" frameX="-38" frameY="-14" frameWidth="857" frameHeight="619"/>
	<SubTexture name="End0070" x="5992" y="2017" width="780" height="605" frameX="-38" frameY="-14" frameWidth="857" frameHeight="619"/>
	<SubTexture name="End0071" x="5992" y="2017" width="780" height="605" frameX="-38" frameY="-14" frameWidth="857" frameHeight="619"/>
	<SubTexture name="End0072" x="5992" y="2017" width="780" height="605" frameX="-38" frameY="-14" frameWidth="857" frameHeight="619"/>
	<SubTexture name="End0073" x="5992" y="2017" width="780" height="605" frameX="-38" frameY="-14" frameWidth="857" frameHeight="619"/>
	<SubTexture name="End0074" x="5992" y="2017" width="780" height="605" frameX="-38" frameY="-14" frameWidth="857" frameHeight="619"/>
	<SubTexture name="End0075" x="5992" y="2017" width="780" height="605" frameX="-38" frameY="-14" frameWidth="857" frameHeight="619"/>
	<SubTexture name="End0076" x="5992" y="2017" width="780" height="605" frameX="-38" frameY="-14" frameWidth="857" frameHeight="619"/>
	<SubTexture name="End0077" x="5992" y="2017" width="780" height="605" frameX="-38" frameY="-14" frameWidth="857" frameHeight="619"/>
	<SubTexture name="End0078" x="5992" y="2017" width="780" height="605" frameX="-38" frameY="-14" frameWidth="857" frameHeight="619"/>
	<SubTexture name="End0079" x="5992" y="2017" width="780" height="605" frameX="-38" frameY="-14" frameWidth="857" frameHeight="619"/>
	<SubTexture name="End0080" x="5992" y="2017" width="780" height="605" frameX="-38" frameY="-14" frameWidth="857" frameHeight="619"/>
	<SubTexture name="End0081" x="5992" y="2017" width="780" height="605" frameX="-38" frameY="-14" frameWidth="857" frameHeight="619"/>
	<SubTexture name="End0082" x="5992" y="2017" width="780" height="605" frameX="-38" frameY="-14" frameWidth="857" frameHeight="619"/>
	<SubTexture name="End0083" x="5992" y="2017" width="780" height="605" frameX="-38" frameY="-14" frameWidth="857" frameHeight="619"/>
	<SubTexture name="End0084" x="5992" y="2017" width="780" height="605" frameX="-38" frameY="-14" frameWidth="857" frameHeight="619"/>
	<SubTexture name="End0085" x="5992" y="2017" width="780" height="605" frameX="-38" frameY="-14" frameWidth="857" frameHeight="619"/>
	<SubTexture name="End0086" x="5992" y="2017" width="780" height="605" frameX="-38" frameY="-14" frameWidth="857" frameHeight="619"/>
	<SubTexture name="End0087" x="5992" y="2017" width="780" height="605" frameX="-38" frameY="-14" frameWidth="857" frameHeight="619"/>
	<SubTexture name="End0088" x="5992" y="2017" width="780" height="605" frameX="-38" frameY="-14" frameWidth="857" frameHeight="619"/>
	<SubTexture name="End0089" x="5992" y="2017" width="780" height="605" frameX="-38" frameY="-14" frameWidth="857" frameHeight="619"/>
	<SubTexture name="Idle0000" x="5653" y="100" width="952" height="969" frameX="-162" frameY="0" frameWidth="1497" frameHeight="1002"/>
	<SubTexture name="Idle0001" x="5653" y="100" width="952" height="969" frameX="-162" frameY="0" frameWidth="1497" frameHeight="1002"/>
	<SubTexture name="Idle0002" x="2190" y="1118" width="954" height="957" frameX="-149" frameY="-13" frameWidth="1497" frameHeight="1002"/>
	<SubTexture name="Idle0003" x="2190" y="1118" width="954" height="957" frameX="-149" frameY="-13" frameWidth="1497" frameHeight="1002"/>
	<SubTexture name="Idle0004" x="4479" y="100" width="1102" height="946" frameX="-132" frameY="-24" frameWidth="1497" frameHeight="1002"/>
	<SubTexture name="Idle0005" x="4479" y="100" width="1102" height="946" frameX="-132" frameY="-24" frameWidth="1497" frameHeight="1002"/>
	<SubTexture name="Idle0006" x="3156" y="100" width="1251" height="946" frameX="-83" frameY="-24" frameWidth="1497" frameHeight="1002"/>
	<SubTexture name="Idle0007" x="3156" y="100" width="1251" height="946" frameX="-83" frameY="-24" frameWidth="1497" frameHeight="1002"/>
	<SubTexture name="Idle0008" x="1669" y="100" width="1415" height="946" frameX="-29" frameY="-24" frameWidth="1497" frameHeight="1002"/>
	<SubTexture name="Idle0009" x="1669" y="100" width="1415" height="946" frameX="-29" frameY="-24" frameWidth="1497" frameHeight="1002"/>
	<SubTexture name="Idle0010" x="100" y="100" width="1497" height="946" frameX="0" frameY="-24" frameWidth="1497" frameHeight="1002"/>
	<SubTexture name="Idle0011" x="100" y="100" width="1497" height="946" frameX="0" frameY="-24" frameWidth="1497" frameHeight="1002"/>
	<SubTexture name="Idle0012" x="6677" y="100" width="973" height="946" frameX="-132" frameY="-24" frameWidth="1497" frameHeight="1002"/>
	<SubTexture name="Idle0013" x="6677" y="100" width="973" height="946" frameX="-132" frameY="-24" frameWidth="1497" frameHeight="1002"/>
	<SubTexture name="Idle0014" x="6677" y="100" width="973" height="946" frameX="-132" frameY="-24" frameWidth="1497" frameHeight="1002"/>
	<SubTexture name="Idle0015" x="6677" y="100" width="973" height="946" frameX="-132" frameY="-24" frameWidth="1497" frameHeight="1002"/>
	<SubTexture name="Idle0016" x="6677" y="100" width="973" height="946" frameX="-132" frameY="-24" frameWidth="1497" frameHeight="1002"/>
	<SubTexture name="Idle0017" x="6677" y="100" width="973" height="946" frameX="-132" frameY="-24" frameWidth="1497" frameHeight="1002"/>
	<SubTexture name="Idle0018" x="6677" y="100" width="973" height="946" frameX="-132" frameY="-24" frameWidth="1497" frameHeight="1002"/>
	<SubTexture name="Idle0019" x="6677" y="100" width="973" height="946" frameX="-132" frameY="-24" frameWidth="1497" frameHeight="1002"/>
	<SubTexture name="Idle0020" x="6677" y="100" width="973" height="946" frameX="-132" frameY="-24" frameWidth="1497" frameHeight="1002"/>
	<SubTexture name="Idle0021" x="6677" y="100" width="973" height="946" frameX="-132" frameY="-24" frameWidth="1497" frameHeight="1002"/>
	<SubTexture name="Idle0022" x="6677" y="100" width="973" height="946" frameX="-132" frameY="-24" frameWidth="1497" frameHeight="1002"/>
	<SubTexture name="Idle0023" x="6677" y="100" width="973" height="946" frameX="-132" frameY="-24" frameWidth="1497" frameHeight="1002"/>
	<SubTexture name="Idle0024" x="6677" y="100" width="973" height="946" frameX="-132" frameY="-24" frameWidth="1497" frameHeight="1002"/>
	<SubTexture name="Idle0025" x="6677" y="100" width="973" height="946" frameX="-132" frameY="-24" frameWidth="1497" frameHeight="1002"/>
	<SubTexture name="Idle0026" x="6677" y="100" width="973" height="946" frameX="-132" frameY="-24" frameWidth="1497" frameHeight="1002"/>
	<SubTexture name="Idle0027" x="6677" y="100" width="973" height="946" frameX="-132" frameY="-24" frameWidth="1497" frameHeight="1002"/>
	<SubTexture name="Idle0028" x="6677" y="100" width="973" height="946" frameX="-132" frameY="-24" frameWidth="1497" frameHeight="1002"/>
	<SubTexture name="Idle0029" x="6677" y="100" width="973" height="946" frameX="-132" frameY="-24" frameWidth="1497" frameHeight="1002"/>
	<SubTexture name="Idle0030" x="6677" y="100" width="973" height="946" frameX="-132" frameY="-24" frameWidth="1497" frameHeight="1002"/>
	<SubTexture name="Idle0031" x="6677" y="100" width="973" height="946" frameX="-132" frameY="-24" frameWidth="1497" frameHeight="1002"/>
	<SubTexture name="Idle0032" x="100" y="1118" width="973" height="946" frameX="-105" frameY="-24" frameWidth="1497" frameHeight="1002"/>
	<SubTexture name="Idle0033" x="100" y="1118" width="973" height="946" frameX="-105" frameY="-24" frameWidth="1497" frameHeight="1002"/>
	<SubTexture name="Idle0034" x="1145" y="1118" width="973" height="946" frameX="-159" frameY="-24" frameWidth="1497" frameHeight="1002"/>
	<SubTexture name="Idle0035" x="1145" y="1118" width="973" height="946" frameX="-159" frameY="-24" frameWidth="1497" frameHeight="1002"/>
	<SubTexture name="Idle0036" x="100" y="1118" width="973" height="946" frameX="-105" frameY="-24" frameWidth="1497" frameHeight="1002"/>
	<SubTexture name="Idle0037" x="100" y="1118" width="973" height="946" frameX="-105" frameY="-24" frameWidth="1497" frameHeight="1002"/>
	<SubTexture name="Idle0038" x="1145" y="1118" width="973" height="946" frameX="-159" frameY="-24" frameWidth="1497" frameHeight="1002"/>
	<SubTexture name="Idle0039" x="4183" y="1118" width="898" height="879" frameX="-163" frameY="-90" frameWidth="1497" frameHeight="1002"/>
	<SubTexture name="Idle0040" x="4183" y="1118" width="898" height="879" frameX="-163" frameY="-90" frameWidth="1497" frameHeight="1002"/>
	<SubTexture name="Idle0041" x="3216" y="1118" width="895" height="885" frameX="-158" frameY="-97" frameWidth="1497" frameHeight="1002"/>
	<SubTexture name="Idle0042" x="3216" y="1118" width="895" height="885" frameX="-158" frameY="-97" frameWidth="1497" frameHeight="1002"/>
	<SubTexture name="Idle0043" x="6677" y="1118" width="803" height="827" frameX="-207" frameY="-175" frameWidth="1497" frameHeight="1002"/>
	<SubTexture name="Idle0044" x="5153" y="1141" width="671" height="793" frameX="-261" frameY="-157" frameWidth="1497" frameHeight="1002"/>
	<SubTexture name="Idle0045" x="5896" y="1141" width="597" height="744" frameX="-236" frameY="-211" frameWidth="1497" frameHeight="1002"/>
	<SubTexture name="Idle0046" x="4384" y="3259" width="583" height="603" frameX="-250" frameY="-328" frameWidth="1497" frameHeight="1002"/>
	<SubTexture name="Idle0047" x="1676" y="3278" width="670" height="489" frameX="-315" frameY="-458" frameWidth="1497" frameHeight="1002"/>
	<SubTexture name="Idle0048" x="5039" y="3259" width="764" height="459" frameX="-269" frameY="-487" frameWidth="1497" frameHeight="1002"/>
	<SubTexture name="Idle0049" x="5039" y="3259" width="764" height="459" frameX="-269" frameY="-487" frameWidth="1497" frameHeight="1002"/>
	<SubTexture name="Idle0050" x="100" y="3260" width="742" height="470" frameX="-280" frameY="-476" frameWidth="1497" frameHeight="1002"/>
	<SubTexture name="Idle0051" x="100" y="3260" width="742" height="470" frameX="-280" frameY="-476" frameWidth="1497" frameHeight="1002"/>
	<SubTexture name="Idle0052" x="914" y="3272" width="690" height="497" frameX="-306" frameY="-449" frameWidth="1497" frameHeight="1002"/>
	<SubTexture name="Idle0053" x="6789" y="3141" width="720" height="490" frameX="-291" frameY="-456" frameWidth="1497" frameHeight="1002"/>
	<SubTexture name="Idle0054" x="6789" y="3141" width="720" height="490" frameX="-291" frameY="-456" frameWidth="1497" frameHeight="1002"/>
	<SubTexture name="Idle0055" x="6789" y="3141" width="720" height="490" frameX="-291" frameY="-456" frameWidth="1497" frameHeight="1002"/>
	<SubTexture name="Idle0056" x="6789" y="3141" width="720" height="490" frameX="-291" frameY="-456" frameWidth="1497" frameHeight="1002"/>
	<SubTexture name="Idle0057" x="6789" y="3141" width="720" height="490" frameX="-291" frameY="-456" frameWidth="1497" frameHeight="1002"/>
	<SubTexture name="Idle0058" x="6789" y="3141" width="720" height="490" frameX="-291" frameY="-456" frameWidth="1497" frameHeight="1002"/>
	<SubTexture name="Idle0059" x="6789" y="3141" width="720" height="490" frameX="-291" frameY="-456" frameWidth="1497" frameHeight="1002"/>
	<SubTexture name="Idle0060" x="6789" y="3141" width="720" height="490" frameX="-291" frameY="-456" frameWidth="1497" frameHeight="1002"/>
	<SubTexture name="Idle0061" x="6789" y="3141" width="720" height="490" frameX="-291" frameY="-456" frameWidth="1497" frameHeight="1002"/>
	<SubTexture name="Idle0062" x="6789" y="3141" width="720" height="490" frameX="-291" frameY="-456" frameWidth="1497" frameHeight="1002"/>
	<SubTexture name="Idle0063" x="6789" y="3141" width="720" height="490" frameX="-291" frameY="-456" frameWidth="1497" frameHeight="1002"/>
	<SubTexture name="Idle0064" x="6789" y="3141" width="720" height="490" frameX="-291" frameY="-456" frameWidth="1497" frameHeight="1002"/>
	<SubTexture name="Idle0065" x="6789" y="3141" width="720" height="490" frameX="-291" frameY="-456" frameWidth="1497" frameHeight="1002"/>
	<SubTexture name="Idle0066" x="6789" y="3141" width="720" height="490" frameX="-291" frameY="-456" frameWidth="1497" frameHeight="1002"/>
	<SubTexture name="Idle0067" x="6789" y="3141" width="720" height="490" frameX="-291" frameY="-456" frameWidth="1497" frameHeight="1002"/>
	<SubTexture name="Idle0068" x="6789" y="3141" width="720" height="490" frameX="-291" frameY="-456" frameWidth="1497" frameHeight="1002"/>
	<SubTexture name="Idle0069" x="6789" y="3141" width="720" height="490" frameX="-291" frameY="-456" frameWidth="1497" frameHeight="1002"/>
	<SubTexture name="Idle0070" x="6789" y="3141" width="720" height="490" frameX="-291" frameY="-456" frameWidth="1497" frameHeight="1002"/>
	<SubTexture name="Idle0071" x="6789" y="3141" width="720" height="490" frameX="-291" frameY="-456" frameWidth="1497" frameHeight="1002"/>
	<SubTexture name="Idle0072" x="6789" y="3141" width="720" height="490" frameX="-291" frameY="-456" frameWidth="1497" frameHeight="1002"/>
	<SubTexture name="Idle0073" x="6789" y="3141" width="720" height="490" frameX="-291" frameY="-456" frameWidth="1497" frameHeight="1002"/>
	<SubTexture name="Idle0074" x="3592" y="3182" width="720" height="490" frameX="-291" frameY="-456" frameWidth="1497" frameHeight="1002"/>
	<SubTexture name="Idle0075" x="3592" y="3182" width="720" height="490" frameX="-291" frameY="-456" frameWidth="1497" frameHeight="1002"/>
	<SubTexture name="Idle0076" x="2608" y="3199" width="720" height="490" frameX="-291" frameY="-456" frameWidth="1497" frameHeight="1002"/>
	<SubTexture name="Idle0077" x="2608" y="3199" width="720" height="490" frameX="-291" frameY="-456" frameWidth="1497" frameHeight="1002"/>
	<SubTexture name="Idle0078" x="100" y="2698" width="759" height="490" frameX="-291" frameY="-456" frameWidth="1497" frameHeight="1002"/>
	<SubTexture name="Idle0079" x="100" y="2698" width="759" height="490" frameX="-291" frameY="-456" frameWidth="1497" frameHeight="1002"/>
	<SubTexture name="Idle0080" x="4971" y="2697" width="774" height="490" frameX="-291" frameY="-456" frameWidth="1497" frameHeight="1002"/>
	<SubTexture name="Idle0081" x="4971" y="2697" width="774" height="490" frameX="-291" frameY="-456" frameWidth="1497" frameHeight="1002"/>
	<SubTexture name="Idle0082" x="4971" y="2697" width="774" height="490" frameX="-291" frameY="-456" frameWidth="1497" frameHeight="1002"/>
	<SubTexture name="Idle0083" x="4971" y="2697" width="774" height="490" frameX="-291" frameY="-456" frameWidth="1497" frameHeight="1002"/>
	<SubTexture name="Idle0084" x="4971" y="2697" width="774" height="490" frameX="-291" frameY="-456" frameWidth="1497" frameHeight="1002"/>
	<SubTexture name="Idle0085" x="4971" y="2697" width="774" height="490" frameX="-291" frameY="-456" frameWidth="1497" frameHeight="1002"/>
	<SubTexture name="Idle0086" x="4971" y="2697" width="774" height="490" frameX="-291" frameY="-456" frameWidth="1497" frameHeight="1002"/>
	<SubTexture name="Idle0087" x="4971" y="2697" width="774" height="490" frameX="-291" frameY="-456" frameWidth="1497" frameHeight="1002"/>
	<SubTexture name="Idle0088" x="4971" y="2697" width="774" height="490" frameX="-291" frameY="-456" frameWidth="1497" frameHeight="1002"/>
	<SubTexture name="Idle0089" x="4971" y="2697" width="774" height="490" frameX="-291" frameY="-456" frameWidth="1497" frameHeight="1002"/>
	<SubTexture name="Idle0090" x="4971" y="2697" width="774" height="490" frameX="-291" frameY="-456" frameWidth="1497" frameHeight="1002"/>
	<SubTexture name="Idle0091" x="4971" y="2697" width="774" height="490" frameX="-291" frameY="-456" frameWidth="1497" frameHeight="1002"/>
	<SubTexture name="Idle0092" x="4971" y="2697" width="774" height="490" frameX="-291" frameY="-456" frameWidth="1497" frameHeight="1002"/>
	<SubTexture name="Idle0093" x="4971" y="2697" width="774" height="490" frameX="-291" frameY="-456" frameWidth="1497" frameHeight="1002"/>
	<SubTexture name="Idle0094" x="4971" y="2697" width="774" height="490" frameX="-291" frameY="-456" frameWidth="1497" frameHeight="1002"/>
	<SubTexture name="Idle0095" x="4971" y="2697" width="774" height="490" frameX="-291" frameY="-456" frameWidth="1497" frameHeight="1002"/>
	<SubTexture name="Loop0000" x="1795" y="2709" width="741" height="497" frameX="0" frameY="0" frameWidth="794" frameHeight="497"/>
	<SubTexture name="Loop0001" x="1867" y="2147" width="794" height="490" frameX="0" frameY="-7" frameWidth="794" frameHeight="497"/>
	<SubTexture name="Loop0002" x="1867" y="2147" width="794" height="490" frameX="0" frameY="-7" frameWidth="794" frameHeight="497"/>
	<SubTexture name="Loop0003" x="2733" y="2637" width="787" height="490" frameX="0" frameY="-7" frameWidth="794" frameHeight="497"/>
	<SubTexture name="Loop0004" x="2733" y="2637" width="787" height="490" frameX="0" frameY="-7" frameWidth="794" frameHeight="497"/>
	<SubTexture name="Loop0005" x="6844" y="2579" width="794" height="490" frameX="0" frameY="-7" frameWidth="794" frameHeight="497"/>
	<SubTexture name="Loop0006" x="6844" y="2579" width="794" height="490" frameX="0" frameY="-7" frameWidth="794" frameHeight="497"/>
	<SubTexture name="Loop0007" x="6844" y="2579" width="794" height="490" frameX="0" frameY="-7" frameWidth="794" frameHeight="497"/>
	<SubTexture name="Loop0008" x="6844" y="2579" width="794" height="490" frameX="0" frameY="-7" frameWidth="794" frameHeight="497"/>
	<SubTexture name="Loop0009" x="6844" y="2579" width="794" height="490" frameX="0" frameY="-7" frameWidth="794" frameHeight="497"/>
	<SubTexture name="Loop0010" x="6844" y="2579" width="794" height="490" frameX="0" frameY="-7" frameWidth="794" frameHeight="497"/>
	<SubTexture name="Loop0011" x="6844" y="2579" width="794" height="490" frameX="0" frameY="-7" frameWidth="794" frameHeight="497"/>
	<SubTexture name="Loop0012" x="6844" y="2579" width="794" height="490" frameX="0" frameY="-7" frameWidth="794" frameHeight="497"/>
	<SubTexture name="Loop0013" x="6844" y="2579" width="794" height="490" frameX="0" frameY="-7" frameWidth="794" frameHeight="497"/>
	<SubTexture name="Loop0014" x="6844" y="2579" width="794" height="490" frameX="0" frameY="-7" frameWidth="794" frameHeight="497"/>
</TextureAtlas>
